Metadata-Version: 1.1
Name: fldi
Version: 0.1.1
Summary: A dependency injection container
Home-page: UNKNOWN
Author: Ádám Gólya
Author-email: UNKNOWN
License: MIT
Platform: UNKNOWN
Classifier: Programming Language :: Python
Classifier: Programming Language :: Python :: 2.7
Classifier: Programming Language :: Python :: 3.6
